[
  {
    "name": "Simulation",
    "traces": [
      "../traces/654.roms_s-523B.champsimtrace.xz"
    ],
    "roi": {
      "cores": [
        {
          "instructions": 200000001,
          "cycles": 256480635,
          "Avg ROB occupancy at mispredict": 351.239, 
          "mispredict": {
            "BRANCH_DIRECT_JUMP": 0,
            "BRANCH_INDIRECT": 0,
            "BRANCH_CONDITIONAL": 19345,
            "BRANCH_DIRECT_CALL": 0,
            "BRANCH_INDIRECT_CALL": 0,
            "BRANCH_RETURN": 0
          }
        }
      ],
      "cpu0_L1I": {
        "LOAD": {
          "hit":611,
          "miss":0
        },
        "RFO": {
          "hit":0,
          "miss":0
        },
        "PREFETCH": {
          "hit":0,
          "miss":0
        },
        "WRITE": {
          "hit":0,
          "miss":0
        },
        "TRANSLATION": {
          "hit":0,
          "miss":0
        },
        "mshr full": 0,
        "prefetch requested": 0,
        "prefetch issued": 0,
        "prefetch filled": 0,
        "prefetch useful": 0,
        "prefetch useless": 0,
        "prefetch late": 0,
        "pf_useful_at_l2_from_l1":          0,
        "pf_late_at_l2_from_l1":          0,
        "pf_useless_at_l2_from_l1":          0,
        "pf_at_l2_to_l1":          0,
        "pf_fill_this_level":          0,
        "miss latency": null,
        "cache queues": {
          "PQ_ACCESS": 0,
          "PQ_FULL": 0,
          "PQ_TO_CACHE": 0,
          "PQ_MERGED": 0,
          "RQ_ACCESS": 643,
          "RQ_MERGED": 32,
          "RQ_FULL": 0,
          "WQ_ACCESS": 0,
          "WQ_MERGED": 0,
          "WQ_FULL": 0
        }
      },
      "cpu0_ITLB": {
        "LOAD": {
          "hit":575,
          "miss":0
        },
        "RFO": {
          "hit":0,
          "miss":0
        },
        "PREFETCH": {
          "hit":0,
          "miss":0
        },
        "WRITE": {
          "hit":0,
          "miss":0
        },
        "TRANSLATION": {
          "hit":0,
          "miss":0
        },
        "mshr full": 0,
        "prefetch requested": 0,
        "prefetch issued": 0,
        "prefetch filled": 0,
        "prefetch useful": 0,
        "prefetch useless": 0,
        "prefetch late": 0,
        "pf_useful_at_l2_from_l1":          0,
        "pf_late_at_l2_from_l1":          0,
        "pf_useless_at_l2_from_l1":          0,
        "pf_at_l2_to_l1":          0,
        "pf_fill_this_level":          0,
        "miss latency": null,
        "cache queues": {
          "PQ_ACCESS": 0,
          "PQ_FULL": 0,
          "PQ_TO_CACHE": 0,
          "PQ_MERGED": 0,
          "RQ_ACCESS": 575,
          "RQ_MERGED": 0,
          "RQ_FULL": 0,
          "WQ_ACCESS": 0,
          "WQ_MERGED": 0,
          "WQ_FULL": 0
        }
      },
      "cpu0_DTLB": {
        "LOAD": {
          "hit":72262643,
          "miss":1175364
        },
        "RFO": {
          "hit":0,
          "miss":0
        },
        "PREFETCH": {
          "hit":0,
          "miss":0
        },
        "WRITE": {
          "hit":0,
          "miss":0
        },
        "TRANSLATION": {
          "hit":0,
          "miss":0
        },
        "mshr full": 157,
        "prefetch requested": 0,
        "prefetch issued": 0,
        "prefetch filled": 0,
        "prefetch useful": 0,
        "prefetch useless": 0,
        "prefetch late": 0,
        "pf_useful_at_l2_from_l1":          0,
        "pf_late_at_l2_from_l1":          0,
        "pf_useless_at_l2_from_l1":          0,
        "pf_at_l2_to_l1":          0,
        "pf_fill_this_level":          0,
        "miss latency": 1.1,
        "cache queues": {
          "PQ_ACCESS": 0,
          "PQ_FULL": 0,
          "PQ_TO_CACHE": 0,
          "PQ_MERGED": 0,
          "RQ_ACCESS": 73445519,
          "RQ_MERGED": 0,
          "RQ_FULL": 7504,
          "WQ_ACCESS": 0,
          "WQ_MERGED": 0,
          "WQ_FULL": 0
        }
      },
      "cpu0_STLB": {
        "LOAD": {
          "hit":670,
          "miss":100609
        },
        "RFO": {
          "hit":0,
          "miss":0
        },
        "PREFETCH": {
          "hit":0,
          "miss":0
        },
        "WRITE": {
          "hit":0,
          "miss":0
        },
        "TRANSLATION": {
          "hit":0,
          "miss":0
        },
        "mshr full": 0,
        "prefetch requested": 0,
        "prefetch issued": 0,
        "prefetch filled": 0,
        "prefetch useful": 0,
        "prefetch useless": 0,
        "prefetch late": 0,
        "pf_useful_at_l2_from_l1":          0,
        "pf_late_at_l2_from_l1":          0,
        "pf_useless_at_l2_from_l1":          0,
        "pf_at_l2_to_l1":          0,
        "pf_fill_this_level":          0,
        "miss latency": 12.3099,
        "cache queues": {
          "PQ_ACCESS": 0,
          "PQ_FULL": 0,
          "PQ_TO_CACHE": 0,
          "PQ_MERGED": 0,
          "RQ_ACCESS": 101279,
          "RQ_MERGED": 0,
          "RQ_FULL": 0,
          "WQ_ACCESS": 0,
          "WQ_MERGED": 0,
          "WQ_FULL": 0
        }
      },
      "cpu0_L1D": {
        "LOAD": {
          "hit":50554824,
          "miss":15319147
        },
        "RFO": {
          "hit":0,
          "miss":0
        },
        "PREFETCH": {
          "hit":277817,
          "miss":2646965
        },
        "WRITE": {
          "hit":2480510,
          "miss":8887917
        },
        "TRANSLATION": {
          "hit":62169,
          "miss":38614
        },
        "mshr full": 67678308,
        "prefetch requested": 2926129,
        "prefetch issued": 2926129,
        "prefetch filled": 2016315,
        "prefetch useful": 2182786,
        "prefetch useless": 344816,
        "prefetch late": 511273,
        "pf_useful_at_l2_from_l1":          0,
        "pf_late_at_l2_from_l1":          0,
        "pf_useless_at_l2_from_l1":          0,
        "pf_at_l2_to_l1":          0,
        "pf_fill_this_level":          0,
        "miss latency": 10.3914,
        "cache queues": {
          "PQ_ACCESS": 2926129,
          "PQ_FULL": 0,
          "PQ_TO_CACHE": 2926129,
          "PQ_MERGED": 1341,
          "RQ_ACCESS": 200196155,
          "RQ_MERGED": 9868138,
          "RQ_FULL": 124453254,
          "WQ_ACCESS": 11686985,
          "WQ_MERGED": 0,
          "WQ_FULL": 318557
        }
      },
      "cpu0_L2C": {
        "LOAD": {
          "hit":5723,
          "miss":1051622
        },
        "RFO": {
          "hit":0,
          "miss":1197770
        },
        "PREFETCH": {
          "hit":52842,
          "miss":2474749
        },
        "WRITE": {
          "hit":1463212,
          "miss":0
        },
        "TRANSLATION": {
          "hit":14478,
          "miss":24136
        },
        "mshr full": 0,
        "prefetch requested": 0,
        "prefetch issued": 0,
        "prefetch filled": 2474745,
        "prefetch useful": 0,
        "prefetch useless": 0,
        "prefetch late": 0,
        "pf_useful_at_l2_from_l1":          0,
        "pf_late_at_l2_from_l1":          0,
        "pf_useless_at_l2_from_l1":          0,
        "pf_at_l2_to_l1":          0,
        "pf_fill_this_level":          0,
        "miss latency": 81.3866,
        "cache queues": {
          "PQ_ACCESS": 2527592,
          "PQ_FULL": 0,
          "PQ_TO_CACHE": 2527592,
          "PQ_MERGED": 0,
          "RQ_ACCESS": 2293729,
          "RQ_MERGED": 0,
          "RQ_FULL": 0,
          "WQ_ACCESS": 1463318,
          "WQ_MERGED": 0,
          "WQ_FULL": 0
        }
      },
      "LLC": {
        "LOAD": {
          "hit": [64],
          "miss": [1051558]
        },
        "RFO": {
          "hit": [2],
          "miss": [1197767]
        },
        "PREFETCH": {
          "hit": [3610],
          "miss": [2471139]
        },
        "WRITE": {
          "hit": [1462601],
          "miss": [0]
        },
        "TRANSLATION": {
          "hit": [4030],
          "miss": [20106]
        },
        "mshr full": 0,
        "prefetch requested": 0,
        "prefetch issued": 0,
        "prefetch filled": 2471135,
        "prefetch useful": 0,
        "prefetch useless": 0,
        "prefetch late": 0,
        "pf_useful_at_l2_from_l1":          0,
        "pf_late_at_l2_from_l1":          0,
        "pf_useless_at_l2_from_l1":          0,
        "pf_at_l2_to_l1":          0,
        "pf_fill_this_level":          0,
        "miss latency": 78.832,
        "cache queues": {
          "PQ_ACCESS": 2474749,
          "PQ_FULL": 0,
          "PQ_TO_CACHE": 2474749,
          "PQ_MERGED": 0,
          "RQ_ACCESS": 2273528,
          "RQ_MERGED": 0,
          "RQ_FULL": 0,
          "WQ_ACCESS": 1462611,
          "WQ_MERGED": 0,
          "WQ_FULL": 0
        }
      },
      "DRAM": [
        {
          "RQ ROW_BUFFER_HIT": 1160540,
          "RQ ROW_BUFFER_MISS": 3580022,
          "PQ FULL": 0,
          "WQ ROW_BUFFER_HIT": 103906,
          "WQ ROW_BUFFER_MISS": 1365381,
          "WQ FULL": 0,
          "AVG DBUS CONGESTED CYCLE": 3.96812
        }
      ]

    },
    "sim": {
      "cores": [
        {
          "instructions": 200000001,
          "cycles": 256480635,
          "Avg ROB occupancy at mispredict": 351.239, 
          "mispredict": {
            "BRANCH_DIRECT_JUMP": 0,
            "BRANCH_INDIRECT": 0,
            "BRANCH_CONDITIONAL": 19345,
            "BRANCH_DIRECT_CALL": 0,
            "BRANCH_INDIRECT_CALL": 0,
            "BRANCH_RETURN": 0
          }
        }
      ],
      "cpu0_L1I": {
        "LOAD": {
          "hit":611,
          "miss":0
        },
        "RFO": {
          "hit":0,
          "miss":0
        },
        "PREFETCH": {
          "hit":0,
          "miss":0
        },
        "WRITE": {
          "hit":0,
          "miss":0
        },
        "TRANSLATION": {
          "hit":0,
          "miss":0
        },
        "mshr full": 0,
        "prefetch requested": 0,
        "prefetch issued": 0,
        "prefetch filled": 0,
        "prefetch useful": 0,
        "prefetch useless": 0,
        "prefetch late": 0,
        "pf_useful_at_l2_from_l1":          0,
        "pf_late_at_l2_from_l1":          0,
        "pf_useless_at_l2_from_l1":          0,
        "pf_at_l2_to_l1":          0,
        "pf_fill_this_level":          0,
        "miss latency": null,
        "cache queues": {
          "PQ_ACCESS": 0,
          "PQ_FULL": 0,
          "PQ_TO_CACHE": 0,
          "PQ_MERGED": 0,
          "RQ_ACCESS": 643,
          "RQ_MERGED": 32,
          "RQ_FULL": 0,
          "WQ_ACCESS": 0,
          "WQ_MERGED": 0,
          "WQ_FULL": 0
        }
      },
      "cpu0_ITLB": {
        "LOAD": {
          "hit":575,
          "miss":0
        },
        "RFO": {
          "hit":0,
          "miss":0
        },
        "PREFETCH": {
          "hit":0,
          "miss":0
        },
        "WRITE": {
          "hit":0,
          "miss":0
        },
        "TRANSLATION": {
          "hit":0,
          "miss":0
        },
        "mshr full": 0,
        "prefetch requested": 0,
        "prefetch issued": 0,
        "prefetch filled": 0,
        "prefetch useful": 0,
        "prefetch useless": 0,
        "prefetch late": 0,
        "pf_useful_at_l2_from_l1":          0,
        "pf_late_at_l2_from_l1":          0,
        "pf_useless_at_l2_from_l1":          0,
        "pf_at_l2_to_l1":          0,
        "pf_fill_this_level":          0,
        "miss latency": null,
        "cache queues": {
          "PQ_ACCESS": 0,
          "PQ_FULL": 0,
          "PQ_TO_CACHE": 0,
          "PQ_MERGED": 0,
          "RQ_ACCESS": 575,
          "RQ_MERGED": 0,
          "RQ_FULL": 0,
          "WQ_ACCESS": 0,
          "WQ_MERGED": 0,
          "WQ_FULL": 0
        }
      },
      "cpu0_DTLB": {
        "LOAD": {
          "hit":72262643,
          "miss":1175364
        },
        "RFO": {
          "hit":0,
          "miss":0
        },
        "PREFETCH": {
          "hit":0,
          "miss":0
        },
        "WRITE": {
          "hit":0,
          "miss":0
        },
        "TRANSLATION": {
          "hit":0,
          "miss":0
        },
        "mshr full": 157,
        "prefetch requested": 0,
        "prefetch issued": 0,
        "prefetch filled": 0,
        "prefetch useful": 0,
        "prefetch useless": 0,
        "prefetch late": 0,
        "pf_useful_at_l2_from_l1":          0,
        "pf_late_at_l2_from_l1":          0,
        "pf_useless_at_l2_from_l1":          0,
        "pf_at_l2_to_l1":          0,
        "pf_fill_this_level":          0,
        "miss latency": 1.1,
        "cache queues": {
          "PQ_ACCESS": 0,
          "PQ_FULL": 0,
          "PQ_TO_CACHE": 0,
          "PQ_MERGED": 0,
          "RQ_ACCESS": 73445519,
          "RQ_MERGED": 0,
          "RQ_FULL": 7504,
          "WQ_ACCESS": 0,
          "WQ_MERGED": 0,
          "WQ_FULL": 0
        }
      },
      "cpu0_STLB": {
        "LOAD": {
          "hit":670,
          "miss":100609
        },
        "RFO": {
          "hit":0,
          "miss":0
        },
        "PREFETCH": {
          "hit":0,
          "miss":0
        },
        "WRITE": {
          "hit":0,
          "miss":0
        },
        "TRANSLATION": {
          "hit":0,
          "miss":0
        },
        "mshr full": 0,
        "prefetch requested": 0,
        "prefetch issued": 0,
        "prefetch filled": 0,
        "prefetch useful": 0,
        "prefetch useless": 0,
        "prefetch late": 0,
        "pf_useful_at_l2_from_l1":          0,
        "pf_late_at_l2_from_l1":          0,
        "pf_useless_at_l2_from_l1":          0,
        "pf_at_l2_to_l1":          0,
        "pf_fill_this_level":          0,
        "miss latency": 12.3099,
        "cache queues": {
          "PQ_ACCESS": 0,
          "PQ_FULL": 0,
          "PQ_TO_CACHE": 0,
          "PQ_MERGED": 0,
          "RQ_ACCESS": 101279,
          "RQ_MERGED": 0,
          "RQ_FULL": 0,
          "WQ_ACCESS": 0,
          "WQ_MERGED": 0,
          "WQ_FULL": 0
        }
      },
      "cpu0_L1D": {
        "LOAD": {
          "hit":50554824,
          "miss":15319147
        },
        "RFO": {
          "hit":0,
          "miss":0
        },
        "PREFETCH": {
          "hit":277817,
          "miss":2646965
        },
        "WRITE": {
          "hit":2480510,
          "miss":8887917
        },
        "TRANSLATION": {
          "hit":62169,
          "miss":38614
        },
        "mshr full": 67678308,
        "prefetch requested": 2926129,
        "prefetch issued": 2926129,
        "prefetch filled": 2016315,
        "prefetch useful": 2182786,
        "prefetch useless": 344816,
        "prefetch late": 511273,
        "pf_useful_at_l2_from_l1":          0,
        "pf_late_at_l2_from_l1":          0,
        "pf_useless_at_l2_from_l1":          0,
        "pf_at_l2_to_l1":          0,
        "pf_fill_this_level":          0,
        "miss latency": 10.3914,
        "cache queues": {
          "PQ_ACCESS": 2926129,
          "PQ_FULL": 0,
          "PQ_TO_CACHE": 2926129,
          "PQ_MERGED": 1341,
          "RQ_ACCESS": 200196155,
          "RQ_MERGED": 9868138,
          "RQ_FULL": 124453254,
          "WQ_ACCESS": 11686985,
          "WQ_MERGED": 0,
          "WQ_FULL": 318557
        }
      },
      "cpu0_L2C": {
        "LOAD": {
          "hit":5723,
          "miss":1051622
        },
        "RFO": {
          "hit":0,
          "miss":1197770
        },
        "PREFETCH": {
          "hit":52842,
          "miss":2474749
        },
        "WRITE": {
          "hit":1463212,
          "miss":0
        },
        "TRANSLATION": {
          "hit":14478,
          "miss":24136
        },
        "mshr full": 0,
        "prefetch requested": 0,
        "prefetch issued": 0,
        "prefetch filled": 2474745,
        "prefetch useful": 0,
        "prefetch useless": 0,
        "prefetch late": 0,
        "pf_useful_at_l2_from_l1":          0,
        "pf_late_at_l2_from_l1":          0,
        "pf_useless_at_l2_from_l1":          0,
        "pf_at_l2_to_l1":          0,
        "pf_fill_this_level":          0,
        "miss latency": 81.3866,
        "cache queues": {
          "PQ_ACCESS": 2527592,
          "PQ_FULL": 0,
          "PQ_TO_CACHE": 2527592,
          "PQ_MERGED": 0,
          "RQ_ACCESS": 2293729,
          "RQ_MERGED": 0,
          "RQ_FULL": 0,
          "WQ_ACCESS": 1463318,
          "WQ_MERGED": 0,
          "WQ_FULL": 0
        }
      },
      "LLC": {
        "LOAD": {
          "hit": [64],
          "miss": [1051558]
        },
        "RFO": {
          "hit": [2],
          "miss": [1197767]
        },
        "PREFETCH": {
          "hit": [3610],
          "miss": [2471139]
        },
        "WRITE": {
          "hit": [1462601],
          "miss": [0]
        },
        "TRANSLATION": {
          "hit": [4030],
          "miss": [20106]
        },
        "mshr full": 0,
        "prefetch requested": 0,
        "prefetch issued": 0,
        "prefetch filled": 2471135,
        "prefetch useful": 0,
        "prefetch useless": 0,
        "prefetch late": 0,
        "pf_useful_at_l2_from_l1":          0,
        "pf_late_at_l2_from_l1":          0,
        "pf_useless_at_l2_from_l1":          0,
        "pf_at_l2_to_l1":          0,
        "pf_fill_this_level":          0,
        "miss latency": 78.832,
        "cache queues": {
          "PQ_ACCESS": 2474749,
          "PQ_FULL": 0,
          "PQ_TO_CACHE": 2474749,
          "PQ_MERGED": 0,
          "RQ_ACCESS": 2273528,
          "RQ_MERGED": 0,
          "RQ_FULL": 0,
          "WQ_ACCESS": 1462611,
          "WQ_MERGED": 0,
          "WQ_FULL": 0
        }
      },
      "DRAM": [
        {
          "RQ ROW_BUFFER_HIT": 1160540,
          "RQ ROW_BUFFER_MISS": 3580022,
          "PQ FULL": 0,
          "WQ ROW_BUFFER_HIT": 103906,
          "WQ ROW_BUFFER_MISS": 1365381,
          "WQ FULL": 0,
          "AVG DBUS CONGESTED CYCLE": 3.96812
        }
      ]

    }
  }
]
